{
 "align_labels_right": 0,
 "creation": "2019-12-19 09:28:00.192401",
 "custom_format": 1,
 "default_print_language": "en",
 "disabled": 0,
 "doc_type": "Sample Daily Report",
 "docstatus": 0,
 "doctype": "Print Format",
 "font": "Default",
 "html": "<meta name=\"pdfkit-orientation\" content=\"Landscape\"/>\n<div class=\"container\">\n      <div class=\"row\">\n        <div class=\"col-xs-12\">\n   \n  {% set letter_head = frappe.get_doc(\"Letter Head\",\"Giico Logo\") %}\n  {% if letter_head %}\n\t{{ letter_head.content }}\n  \n  {% endif %}\n  </div>\n  </div>\n    <div class=\"row\">\n        <div class=\"col-xs-12\">\n            <h7><center><b>TOPOGRAPHICAL SURVEY WORKS<br>KOC RFP- 2036104- EVALUATION OF STRUCTURAL INTERGRITY OF KOC OFFICE COMPLEX<br>DAILY REPORT\t\t\t\t\t\t\n<br>Date:{{frappe.utils.formatdate(doc.date) or \"\"}}</b></center></h7>\n            <h4><center><b>CLIENT:{{doc.client or\"\"}}</b></center></h4>\n              <table class =\"table table-bordered\" border=\"1\">\n    <tr>\n        <td height=\"60\" colspan=\"3\"><b><center>Work Performed:</center></b></td>\n           <td height=\"60\" colspan=\"9\">{{doc.work_performed or \"\"}}</td>\n    </tr>\n    <tr>\n        <th colspan=\"2\"><b>Item</b></th>\n          <th colspan=\"4\"><b>Description</b></th>\n            <th colspan=\"1\"><b>Total Quantity</b></th>\n              <th colspan=\"1\"><b>Completed Qty </b></th>\n               <th colspan=\"1\"><b>Balance Qty</b></th>\n              <th colspan=\"1\"><b>Completed %</b></th>\n               <th colspan=\"1\"><b>Balance %</b></th>\n    </tr>\n    <tr>\n        <td colspan=\"2\"><b>1. FIELD WORK</b></td>\n          <td colspan=\"4\"><b></b></td>\n            <td colspan=\"1\"><b></b></td>\n              <td colspan=\"1\"><b> </b></td>\n               <td colspan=\"1\"><b></b></td>\n              <td colspan=\"1\"><b></b></td>\n               <td colspan=\"1\"></td>\n               {%- for row in doc.field_work -%}\n    </tr>\n    <tr>\n        <td colspan=\"2\">{{row.item or \"\"}}</td>\n          <td colspan=\"4\">{{row.description or \"\"}}</td>\n            <td colspan=\"1\">{{row.total_quantity}}</td>\n              <td colspan=\"1\">{{row.completed_qty}}</td>\n               <td colspan=\"1\">{{row.balance_qty}}</td>\n              <td colspan=\"1\">{{row.completed}}%</td>\n               <td colspan=\"1\">{{row.balance}}%</td>\n               </tr>\n               {%- endfor -%}\n                <tr>\n        <td height=\"60\" colspan=\"3\"><b><center>Work Plan For Next Day</center></b></td>\n           <td height=\"60\" colspan=\"9\">{{doc.work_plan or \"\"}}</td>\n           </tr>\n            <tr>\n        <td height=\"60\" colspan=\"3\"><b><center>Crew</center></b></td>\n           <td height=\"60\" colspan=\"9\">{{doc.crew or \"\"}}</td>\n    </tr>\n    \n</table>    \n         </div>\n    </div>\n</div>",
 "idx": 0,
 "line_breaks": 0,
 "modified": "2019-12-19 13:26:52.771125",
 "modified_by": "Administrator",
 "module": "Topography and Marine Survey",
 "name": "Sample Daily Report",
 "owner": "Administrator",
 "print_format_builder": 0,
 "print_format_type": "Jinja",
 "raw_printing": 0,
 "show_section_headings": 0,
 "standard": "Yes"
}